HCRSimPY/__init__.py
HCRSimPY/data/__init__.py
HCRSimPY/light_schedules/LightSchedule.py
HCRSimPY/light_schedules/__init__.py
HCRSimPY/light_schedules/parse_data.py
HCRSimPY/models/__init__.py
HCRSimPY/models/singlepop_model.py
HCRSimPY/models/twopop_model.py
HCRSimPY/models/vdp_forger99_model.py
HCRSimPY/plots/__init__.py
HCRSimPY/plots/actogram.py
HCRSimPY/plots/latexify.py
HCRSimPY/plots/stroboscopic.py
HCRSimPY/utils/__init__.py
HCRSimPY/utils/circstats.py
HCRSimPY/utils/circular_stats.py
tests/__init__.py
tests/spmodel_test.py
tests/test_vdp_simple.py
HCRSimPY-1.0.7.dist-info/LICENSE
HCRSimPY-1.0.7.dist-info/METADATA
HCRSimPY-1.0.7.dist-info/WHEEL
HCRSimPY-1.0.7.dist-info/top_level.txt
HCRSimPY-1.0.7.dist-info/RECORD
