Metadata-Version: 2.1
Name: HCRSimPY
Version: 1.0.7
Summary: A package to simulate and analyze human circadian rhythms.
Home-page: https://github.com/khannay/HCRSimPY
Author: Kevin Hannay
Author-email: khannay24@gmail.com
Classifier: Programming Language :: Python :: 3
Classifier: License :: OSI Approved :: GNU General Public License v3 (GPLv3)
Requires-Python: >=3.8
License-File: LICENSE
Requires-Dist: scipy (>=1.3)
